urchintai_client/__init__.py
urchintai_client/constants.py
urchintai_client/request_sender.py
urchintai_client/session_manager.py
urchintai_client/ur_client.py
urchintai_client/ur_parser.py
urchintai_client-1.0.0.dist-info/LICENSE.txt
urchintai_client-1.0.0.dist-info/METADATA
urchintai_client-1.0.0.dist-info/WHEEL
urchintai_client-1.0.0.dist-info/top_level.txt
urchintai_client-1.0.0.dist-info/RECORD
