Metadata-Version: 2.1
Name: urchintai-client
Version: 1.0.0
Summary: Client to call UR Chintai API (UR都市機構)
Home-page: https://github.com/duongntbk/urchintai-client
Author: Nguyen Thai Duong
Author-email: duongnt.bk@gmail.com
License: UNKNOWN
Platform: UNKNOWN
Classifier: Programming Language :: Python :: 3
Classifier: License :: OSI Approved :: MIT License
Classifier: Operating System :: OS Independent
License-File: LICENSE.txt
Requires-Dist: aiohttp (>=3.7.4)
Requires-Dist: beautifulsoup4 (>=4.9.3)
